{
  "project_info": {
    "project_number": "120912824491",
    "project_id": "piano-test-26f1c",
    "storage_bucket": "piano-test-26f1c.appspot.com"
  },
  "client": [
    {
      "client_info": {
        "mobilesdk_app_id": "1:120912824491:android:7b61623f6eb01fe9138fee",
        "android_client_info": {
          "package_name": "com.bhogayatakb.piano"
        }
      },
      "oauth_client": [
        {
          "client_id": "120912824491-a7omp65hnoh1medv356pu6pt4dcege20.apps.googleusercontent.com",
          "client_type": 1,
          "android_info": {
            "package_name": "com.bhogayatakb.piano",
            "certificate_hash": "1d507db8452572f6f1a9e6bbfd076f940d4f876d"
          }
        },
        {
          "client_id": "120912824491-lff8r4q8h5vm2nlv4sv5vhdfe3q04fic.apps.googleusercontent.com",
          "client_type": 1,
          "android_info": {
            "package_name": "com.bhogayatakb.piano",
            "certificate_hash": "fd3487442119bdbf9664bd16978ddc0d8c5d2341"
          }
        },
        {
          "client_id": "120912824491-4f28cd9is0rjg4g48vt8el1o2ulvpfit.apps.googleusercontent.com",
          "client_type": 3
        }
      ],
      "api_key": [
        {
          "current_key": "AIzaSyC6he2vTVI9yJVtBKOKXGjFpqWY-iwdnGk"
        }
      ],
      "services": {
        "appinvite_service": {
          "other_platform_oauth_client": [
            {
              "client_id": "120912824491-4f28cd9is0rjg4g48vt8el1o2ulvpfit.apps.googleusercontent.com",
              "client_type": 3
            }
          ]
        }
      }
    }
  ],
  "configuration_version": "1"
}